{"s_8104800009999-235260":{"zone_name":"Space8104","zone_summerrad":null,"zone_winterrad":null,"zone_standard":"climatezone3_GB/T51350-2019_RESIDENTIAL","zone_wallU":"0.35","zone_winU":"1.8","zone_win_SHGC":"0.4","zone_c_temp":"26","zone_c_hum":"0.4","zone_h_temp":"18","zone_collingEER":"2.5","zone_HeatingEER":"2","zone_work_start":"0","zone_work_end":"23","zone_ppsm":"0.0196","zone_pfav":"30","zone_popheat":"88","zone_equipment":"3.8","zone_lighting":"5","zone_inflitration":"0.5","zone_nightACH":"1\n"},"s_8104800000999-235260":{"zone_name":"Space8104","zone_summerrad":null,"zone_winterrad":null,"zone_standard":"climatezone3_GB/T51350-2019_RESIDENTIAL","zone_wallU":"0.35","zone_winU":"1.8","zone_win_SHGC":"0.4","zone_c_temp":"26","zone_c_hum":"0.4","zone_h_temp":"18","zone_collingEER":"2.5","zone_HeatingEER":"2","zone_work_start":"0","zone_work_end":"23","zone_ppsm":"0.0196","zone_pfav":"30","zone_popheat":"88","zone_equipment":"3.8","zone_lighting":"5","zone_inflitration":"0.5","zone_nightACH":"1\n"},"s_81046000099-235260":{"zone_name":"Space8104","zone_summerrad":null,"zone_winterrad":null,"zone_standard":"climatezone3_GB/T51350-2019_RESIDENTIAL","zone_wallU":"0.35","zone_winU":"1.8","zone_win_SHGC":"0.4","zone_c_temp":"26","zone_c_hum":"0.4","zone_h_temp":"18","zone_collingEER":"2.5","zone_HeatingEER":"2","zone_work_start":"0","zone_work_end":"23","zone_ppsm":"0.0196","zone_pfav":"30","zone_popheat":"88","zone_equipment":"3.8","zone_lighting":"5","zone_inflitration":"0.5","zone_nightACH":"1\n"},"s_1214400110-74-230":{"zone_name":"Space1214","zone_summerrad":null,"zone_winterrad":null,"zone_standard":"climatezone3_GB/T51350-2019_RESIDENTIAL","zone_wallU":"0.35","zone_winU":"1.8","zone_win_SHGC":"0.4","zone_c_temp":"26","zone_c_hum":"0.4","zone_h_temp":"18","zone_collingEER":"2.5","zone_HeatingEER":"2","zone_work_start":"0","zone_work_end":"23","zone_ppsm":"0.0196","zone_pfav":"30","zone_popheat":"88","zone_equipment":"3.8","zone_lighting":"5","zone_inflitration":"0.5","zone_nightACH":"1\n"},"s_1214402910-74-230":{"zone_name":"Space1214","zone_summerrad":null,"zone_winterrad":null,"zone_standard":"climatezone3_GB/T51350-2019_RESIDENTIAL","zone_wallU":"0.35","zone_winU":"1.8","zone_win_SHGC":"0.4","zone_c_temp":"26","zone_c_hum":"0.4","zone_h_temp":"18","zone_collingEER":"2.5","zone_HeatingEER":"2","zone_work_start":"0","zone_work_end":"23","zone_ppsm":"0.0196","zone_pfav":"30","zone_popheat":"88","zone_equipment":"3.8","zone_lighting":"5","zone_inflitration":"0.5","zone_nightACH":"1\n"},"s_1214401910000":{"zone_name":"Space1214","zone_summerrad":null,"zone_winterrad":null,"zone_standard":"climatezone3_GB/T51350-2019_RESIDENTIAL","zone_wallU":"0.35","zone_winU":"1.8","zone_win_SHGC":"0.4","zone_c_temp":"26","zone_c_hum":"0.4","zone_h_temp":"18","zone_collingEER":"2.5","zone_HeatingEER":"2","zone_work_start":"0","zone_work_end":"23","zone_ppsm":"0.0196","zone_pfav":"30","zone_popheat":"88","zone_equipment":"3.8","zone_lighting":"5","zone_inflitration":"0.5","zone_nightACH":"1\n"},"s_8104800009999196-1320":{"zone_name":"Space8104","zone_summerrad":null,"zone_winterrad":null,"zone_standard":"climatezone3_GB/T51350-2019_RESIDENTIAL","zone_wallU":"0.35","zone_winU":"1.8","zone_win_SHGC":"0.4","zone_c_temp":"26","zone_c_hum":"0.4","zone_h_temp":"18","zone_collingEER":"2.5","zone_HeatingEER":"2","zone_work_start":"0","zone_work_end":"23","zone_ppsm":"0.0196","zone_pfav":"30","zone_popheat":"88","zone_equipment":"3.8","zone_lighting":"5","zone_inflitration":"0.5","zone_nightACH":"1\n"},"s_810440099-287-1160":{"zone_name":"Space8104","zone_summerrad":null,"zone_winterrad":null,"zone_standard":"climatezone3_GB/T51350-2019_RESIDENTIAL","zone_wallU":"0.35","zone_winU":"1.8","zone_win_SHGC":"0.4","zone_c_temp":"26","zone_c_hum":"0.4","zone_h_temp":"18","zone_collingEER":"2.5","zone_HeatingEER":"2","zone_work_start":"0","zone_work_end":"23","zone_ppsm":"0.0196","zone_pfav":"30","zone_popheat":"88","zone_equipment":"3.8","zone_lighting":"5","zone_inflitration":"0.5","zone_nightACH":"1\n"},"s_810460009910296-920":{"zone_name":"Space8104","zone_summerrad":null,"zone_winterrad":null,"zone_standard":"climatezone3_GB/T51350-2019_RESIDENTIAL","zone_wallU":"0.35","zone_winU":"1.8","zone_win_SHGC":"0.4","zone_c_temp":"26","zone_c_hum":"0.4","zone_h_temp":"18","zone_collingEER":"2.5","zone_HeatingEER":"2","zone_work_start":"0","zone_work_end":"23","zone_ppsm":"0.0196","zone_pfav":"30","zone_popheat":"88","zone_equipment":"3.8","zone_lighting":"5","zone_inflitration":"0.5","zone_nightACH":"1\n"},"s_5034800000019-118390":{"zone_name":"Space5034","zone_summerrad":null,"zone_winterrad":null,"zone_standard":"climatezone3_GB/T51350-2019_RESIDENTIAL","zone_wallU":"0.35","zone_winU":"1.8","zone_win_SHGC":"0.4","zone_c_temp":"26","zone_c_hum":"0.4","zone_h_temp":"18","zone_collingEER":"2.5","zone_HeatingEER":"2","zone_work_start":"0","zone_work_end":"23","zone_ppsm":"0.0196","zone_pfav":"30","zone_popheat":"88","zone_equipment":"3.8","zone_lighting":"5","zone_inflitration":"0.5","zone_nightACH":"1\n"},"s_51948000099910-23-1050":{"zone_name":"Space5194","zone_summerrad":null,"zone_winterrad":null,"zone_standard":"climatezone3_GB/T51350-2019_RESIDENTIAL","zone_wallU":"0.35","zone_winU":"1.8","zone_win_SHGC":"0.4","zone_c_temp":"26","zone_c_hum":"0.4","zone_h_temp":"18","zone_collingEER":"2.5","zone_HeatingEER":"2","zone_work_start":"0","zone_work_end":"23","zone_ppsm":"0.0196","zone_pfav":"30","zone_popheat":"88","zone_equipment":"3.8","zone_lighting":"5","zone_inflitration":"0.5","zone_nightACH":"1\n"},"s_503460002910260-870":{"zone_name":"Space5034","zone_summerrad":null,"zone_winterrad":null,"zone_standard":"climatezone3_GB/T51350-2019_RESIDENTIAL","zone_wallU":"0.35","zone_winU":"1.8","zone_win_SHGC":"0.4","zone_c_temp":"26","zone_c_hum":"0.4","zone_h_temp":"18","zone_collingEER":"2.5","zone_HeatingEER":"2","zone_work_start":"0","zone_work_end":"23","zone_ppsm":"0.0196","zone_pfav":"30","zone_popheat":"88","zone_equipment":"3.8","zone_lighting":"5","zone_inflitration":"0.5","zone_nightACH":"1\n"},"s_810440099000":{"zone_name":"Space8104","zone_summerrad":null,"zone_winterrad":null,"zone_standard":"climatezone3_GB/T51350-2019_RESIDENTIAL","zone_wallU":"0.35","zone_winU":"1.8","zone_win_SHGC":"0.4","zone_c_temp":"26","zone_c_hum":"0.4","zone_h_temp":"18","zone_collingEER":"2.5","zone_HeatingEER":"2","zone_work_start":"0","zone_work_end":"23","zone_ppsm":"0.0196","zone_pfav":"30","zone_popheat":"88","zone_equipment":"3.8","zone_lighting":"5","zone_inflitration":"0.5","zone_nightACH":"1\n"},"s_5034600002977700":{"zone_name":"Space5034","zone_summerrad":null,"zone_winterrad":null,"zone_standard":"climatezone3_GB/T51350-2019_RESIDENTIAL","zone_wallU":"0.35","zone_winU":"1.8","zone_win_SHGC":"0.4","zone_c_temp":"26","zone_c_hum":"0.4","zone_h_temp":"18","zone_collingEER":"2.5","zone_HeatingEER":"2","zone_work_start":"0","zone_work_end":"23","zone_ppsm":"0.0196","zone_pfav":"30","zone_popheat":"88","zone_equipment":"3.8","zone_lighting":"5","zone_inflitration":"0.5","zone_nightACH":"1\n"},"s_503480000005977970":{"zone_name":"Space5034","zone_summerrad":null,"zone_winterrad":null,"zone_standard":"climatezone3_GB/T51350-2019_RESIDENTIAL","zone_wallU":"0.35","zone_winU":"1.8","zone_win_SHGC":"0.4","zone_c_temp":"26","zone_c_hum":"0.4","zone_h_temp":"18","zone_collingEER":"2.5","zone_HeatingEER":"2","zone_work_start":"0","zone_work_end":"23","zone_ppsm":"0.0196","zone_pfav":"30","zone_popheat":"88","zone_equipment":"3.8","zone_lighting":"5","zone_inflitration":"0.5","zone_nightACH":"1\n"},"s_87841000000599910940799020":{"zone_name":"Space8784","zone_summerrad":null,"zone_winterrad":null,"zone_standard":"climatezone3_GB/T51350-2019_RESIDENTIAL","zone_wallU":"0.35","zone_winU":"1.8","zone_win_SHGC":"0.4","zone_c_temp":"26","zone_c_hum":"0.4","zone_h_temp":"18","zone_collingEER":"2.5","zone_HeatingEER":"2","zone_work_start":"0","zone_work_end":"23","zone_ppsm":"0.0196","zone_pfav":"30","zone_popheat":"88","zone_equipment":"3.8","zone_lighting":"5","zone_inflitration":"0.5","zone_nightACH":"1\n"},"s_878410000005999109388979679":{"zone_name":"Space8784","zone_summerrad":null,"zone_winterrad":null,"zone_standard":"climatezone3_GB/T51350-2019_RESIDENTIAL","zone_wallU":"0.35","zone_winU":"1.8","zone_win_SHGC":"0.4","zone_c_temp":"26","zone_c_hum":"0.4","zone_h_temp":"18","zone_collingEER":"2.5","zone_HeatingEER":"2","zone_work_start":"0","zone_work_end":"23","zone_ppsm":"0.0196","zone_pfav":"30","zone_popheat":"88","zone_equipment":"3.8","zone_lighting":"5","zone_inflitration":"0.5","zone_nightACH":"1\n"}}